{
  "actionDocMetaList": [
    {
      "url": "/root/",
      "typeName": "org.docksidestage.app.web.RootAction",
      "simpleTypeName": "RootAction",
      "description": "@author jflute",
      "typeComment": "@author jflute",
      "fieldTypeDocMetaList": [],
      "methodName": "index",
      "methodComment": null,
      "annotationList": [
        "AllowAnyoneAccess",
        "Execute"
      ],
      "parameterTypeDocMetaList": [],
      "formTypeDocMeta": null,
      "returnTypeDocMeta": {
        "name": null,
        "publicName": null,
        "typeName": "org.lastaflute.web.response.HtmlResponse",
        "simpleTypeName": "HtmlResponse",
        "value": "HtmlResponse.fromForwardPath(\"/index.html\")",
        "description": null,
        "comment": null,
        "annotationList": [],
        "nestTypeDocMetaList": []
      },
      "fileLineCount": 7,
      "methodLineCount": 3
    }
  ]
}